namanager/__init__.py
namanager/archieve_manager.py
namanager/core.py
namanager/enums.py
namanager/logger.py
namanager/main.py
namanager/util.py
namanager-0.3.2.data/scripts/namanager
namanager-0.3.2.dist-info/METADATA
namanager-0.3.2.dist-info/RECORD
namanager-0.3.2.dist-info/WHEEL
namanager-0.3.2.dist-info/top_level.txt
