Metadata-Version: 2.1
Name: namanager
Version: 0.3.2
Summary: A file or/and directory name manager which could determinenames are/aren't expectable, and you could also automatically rename it.
Home-page: https://github.com/iattempt/namanager
Author: Ernest Chang (https://github.com/iattempt) and Arnav Borborah (https://github.com/arnavb) 
Author-email: iattempt.net@gmail.com, arnavborborah11@gmail.com
License: GNU General Public License v3.0
Keywords: namanager,name,manager,checker,formatter,filename
Platform: UNKNOWN
Classifier: Topic :: Software Development
Classifier: Topic :: Utilities
Classifier: License :: OSI Approved :: GNU General Public License v3 (GPLv3)
Classifier: Programming Language :: Python
Classifier: Programming Language :: Python :: 2.7
Classifier: Programming Language :: Python :: 3.3
Classifier: Programming Language :: Python :: 3.4
Classifier: Programming Language :: Python :: 3.5
Classifier: Programming Language :: Python :: 3.6
Classifier: Operating System :: OS Independent
Classifier: Intended Audience :: Customer Service
Classifier: Intended Audience :: Developers
Classifier: Intended Audience :: System Administrators
Classifier: Environment :: Console
Classifier: Natural Language :: English
Requires-Python: >=2.7,!=3.0.*,!=3.1.*,!=3.2.*,
Requires-Dist: dicttoxml (>=1.3.1)
Requires-Dist: xmltodict (>=0.11.0)
